Metadata-Version: 2.1
Name: webcandy-client
Version: 0.1.5
Summary: Client-side code for communicating with a Webcandy server.
Home-page: https://github.com/gcpreston/webcandy-client
Author: Graham Preston
Author-email: graham.preston@gmail.com
License: UNKNOWN
Project-URL: Source, https://github.com/gcpreston/webcandy-client
Platform: UNKNOWN
Classifier: Development Status :: 3 - Alpha
Classifier: License :: OSI Approved :: MIT License
Classifier: Programming Language :: Python :: 3
Classifier: Programming Language :: Python :: 3.7
